adb_push_create/README.MD
adb_push_create/__init__.py
adb_push_create/requirements.txt
adb_push_create/thirdparty.json
adb_push_create-0.11.dist-info/LICENSE.rst
adb_push_create-0.11.dist-info/METADATA
adb_push_create-0.11.dist-info/WHEEL
adb_push_create-0.11.dist-info/top_level.txt
adb_push_create-0.11.dist-info/RECORD
