Metadata-Version: 2.1
Name: adb-push-create
Version: 0.11
Summary: creates [nested] folders and pushes files with ADB
Home-page: https://github.com/hansalemaos/adb_push_create
Author: Johannes Fischer
Author-email: aulasparticularesdealemaosp@gmail.com
License: MIT
Keywords: adb
Classifier: Development Status :: 4 - Beta
Classifier: Programming Language :: Python :: 3 :: Only
Classifier: Programming Language :: Python :: 3.10
Classifier: Topic :: Software Development :: Libraries :: Python Modules
Classifier: Topic :: Utilities
License-File: LICENSE.rst
